{
  "win3": "KDI",
  "separatorList": ",",
  "number": {
    "symbolPositiveInfinity": "Infinity",
    "symbolPerMille": "‰",
    "symbolNegativeInfinity": "-Infinity",
    "symbolNaN": "NaN",
    "symbolCurrency": "₹",
    "signPositive": "+",
    "signNegative": "-",
    "separatorGroupPercent": ",",
    "separatorGroupNumber": ",",
    "separatorGroupCurrency": ",",
    "separatorDecimalPercent": ".",
    "separatorDecimalNumber": ".",
    "separatorDecimalCurrency": ".",
    "patternPositivePercent": 0,
    "patternPositiveCurrency": 2,
    "patternNegativePercent": 0,
    "patternNegativeNumber": 1,
    "patternNegativeCurrency": 12,
    "groupSizesPercent": [
      3,
      2
    ],
    "groupSizesNumber": [
      3,
      2
    ],
    "groupSizesCurrency": [
      3,
      2
    ],
    "decimalDigitsPercent": 2,
    "decimalDigitsNumber": 2,
    "decimalDigitsCurrency": 2
  },
  "nameRegionNative": "ಭಾರತ",
  "nameRegionEnglish": "India",
  "nameNative": "ಕನ್ನಡ",
  "nameEnglish": "Kannada",
  "nameDisplay": "Kannada (India)",
  "nameCalendar": "Gregorian",
  "lcid": 1099,
  "isRightToLeft": false,
  "iso3": "kan",
  "iso2": "kn",
  "isNeutral": false,
  "ietf": "kn-IN",
  "dateTime": {
    "separatorTime": ":",
    "separatorDate": "-",
    "patternYearMonth": "MMMM, yyyy",
    "patternUniversalSortable": "yyyy'-'MM'-'dd HH':'mm':'ss'Z'",
    "patternTimeShort": "HH:mm",
    "patternTimeLong": "HH:mm:ss",
    "patternRfc1123": "ddd, dd MMM yyyy HH':'mm':'ss 'GMT'",
    "patternMonthDay": "MMMM d",
    "patternDateTimeSortable": "yyyy'-'MM'-'dd'T'HH':'mm':'ss",
    "patternDateTimeFull": "dd MMMM yyyy HH:mm:ss",
    "patternDateShort": "dd-MM-yy",
    "patternDateLong": "dd MMMM yyyy",
    "nameMonthGenitivesAbbreviated": [
      "ಜನ.",
      "ಫೆಬ್ರು.",
      "ಮಾ",
      "ಏಪ್ರಿ.",
      "ಮೇ",
      "ಜೂ",
      "ಜು.",
      "ಆಗ.",
      "ಸೆಪ್ಟೆಂ.",
      "ಅಕ್ಟೋ.",
      "ನವೆಂ.",
      "ಡಿಸೆಂ.",
      ""
    ],
    "nameMonthGenitives": [
      "ಜನವರಿ",
      "ಫೆಬ್ರವರಿ",
      "ಮಾರ್ಚ್",
      "ಏಪ್ರಿಲ್",
      "ಮೇ",
      "ಜೂನ್",
      "ಜುಲೈ",
      "ಆಗಸ್ಟ್",
      "ಸಪ್ಟೆಂಬರ್",
      "ಅಕ್ಟೋಬರ್",
      "ನವೆಂಬರ್",
      "ಡಿಸೆಂಬರ್",
      ""
    ],
    "nameMonthsAbbreviated": [
      "ಜನ.",
      "ಫೆಬ್ರು.",
      "ಮಾ",
      "ಏಪ್ರಿ.",
      "ಮೇ",
      "ಜೂ",
      "ಜು.",
      "ಆಗ.",
      "ಸೆಪ್ಟೆಂ.",
      "ಅಕ್ಟೋ.",
      "ನವೆಂ.",
      "ಡಿಸೆಂ.",
      ""
    ],
    "nameMonths": [
      "ಜನವರಿ",
      "ಫೆಬ್ರವರಿ",
      "ಮಾರ್ಚ್",
      "ಏಪ್ರಿಲ್",
      "ಮೇ",
      "ಜೂನ್",
      "ಜುಲೈ",
      "ಆಗಸ್ಟ್",
      "ಸಪ್ಟೆಂಬರ್",
      "ಅಕ್ಟೋಬರ್",
      "ನವೆಂಬರ್",
      "ಡಿಸೆಂಬರ್",
      ""
    ],
    "nameDaysShortest": [
      "ರ",
      "ಸೋ",
      "ಮಂ",
      "ಬು",
      "ಗು",
      "ಶು",
      "ಶ"
    ],
    "nameDaysAbbreviated": [
      "ರವಿ",
      "ಸೋಮ",
      "ಮಂಗಳ",
      "ಬುಧ",
      "ಗುರು",
      "ಶುಕ್ರ",
      "ಶನಿ"
    ],
    "nameDays": [
      "ರವಿವಾರ",
      "ಸೋಮವಾರ",
      "ಮಂಗಳವಾರ",
      "ಬುಧವಾರ",
      "ಗುರುವಾರ",
      "ಶುಕ್ರವಾರ",
      "ಶನಿವಾರ"
    ],
    "nameCalendarNative": "ಗ್ರಿಗೋರಿಯನ್ ಕ್ಯಾಲೆಂಡರ್",
    "nameCalendar": "Gregorian",
    "firstDayOfWeekName": "Sunday",
    "firstDayOfWeekIndex": 0,
    "designatorPm": "PM",
    "designatorAm": "AM",
    "calendarWeekRuleName": "FirstDay",
    "calendarWeekRuleIndex": 0
  },
  "code": "kn-IN"
}