{
  "win3": "LTH",
  "separatorList": ";",
  "number": {
    "symbolPositiveInfinity": "begalybė",
    "symbolPerMille": "‰",
    "symbolNegativeInfinity": "-begalybė",
    "symbolNaN": "NaN",
    "symbolCurrency": "Lt",
    "signPositive": "+",
    "signNegative": "-",
    "separatorGroupPercent": " ",
    "separatorGroupNumber": " ",
    "separatorGroupCurrency": ".",
    "separatorDecimalPercent": ",",
    "separatorDecimalNumber": ",",
    "separatorDecimalCurrency": ",",
    "patternPositivePercent": 1,
    "patternPositiveCurrency": 3,
    "patternNegativePercent": 1,
    "patternNegativeNumber": 1,
    "patternNegativeCurrency": 8,
    "groupSizesPercent": [
      3
    ],
    "groupSizesNumber": [
      3
    ],
    "groupSizesCurrency": [
      3
    ],
    "decimalDigitsPercent": 2,
    "decimalDigitsNumber": 2,
    "decimalDigitsCurrency": 2
  },
  "nameRegionNative": "Lietuva",
  "nameRegionEnglish": "Lithuania",
  "nameNative": "lietuvių",
  "nameEnglish": "Lithuanian",
  "nameDisplay": "Lithuanian (Lithuania)",
  "nameCalendar": "Gregorian",
  "lcid": 1063,
  "isRightToLeft": false,
  "iso3": "lit",
  "iso2": "lt",
  "isNeutral": false,
  "ietf": "lt-LT",
  "dateTime": {
    "separatorTime": ":",
    "separatorDate": "-",
    "patternYearMonth": "yyyy 'm.' MMMM",
    "patternUniversalSortable": "yyyy'-'MM'-'dd HH':'mm':'ss'Z'",
    "patternTimeShort": "HH:mm",
    "patternTimeLong": "HH:mm:ss",
    "patternRfc1123": "ddd, dd MMM yyyy HH':'mm':'ss 'GMT'",
    "patternMonthDay": "MMMM d 'd.'",
    "patternDateTimeSortable": "yyyy'-'MM'-'dd'T'HH':'mm':'ss",
    "patternDateTimeFull": "yyyy 'm.' MMMM d 'd.' HH:mm:ss",
    "patternDateShort": "yyyy-MM-dd",
    "patternDateLong": "yyyy 'm.' MMMM d 'd.'",
    "nameMonthGenitivesAbbreviated": [
      "saus.",
      "vas.",
      "kov.",
      "bal.",
      "geg.",
      "birž.",
      "liep.",
      "rugp.",
      "rugs.",
      "spal.",
      "lapkr.",
      "gruod.",
      ""
    ],
    "nameMonthGenitives": [
      "sausis",
      "vasaris",
      "kovas",
      "balandis",
      "gegužė",
      "birželis",
      "liepa",
      "rugpjūtis",
      "rugsėjis",
      "spalis",
      "lapkritis",
      "gruodis",
      ""
    ],
    "nameMonthsAbbreviated": [
      "saus.",
      "vas.",
      "kov.",
      "bal.",
      "geg.",
      "birž.",
      "liep.",
      "rugp.",
      "rugs.",
      "spal.",
      "lapkr.",
      "gruod.",
      ""
    ],
    "nameMonths": [
      "sausis",
      "vasaris",
      "kovas",
      "balandis",
      "gegužė",
      "birželis",
      "liepa",
      "rugpjūtis",
      "rugsėjis",
      "spalis",
      "lapkritis",
      "gruodis",
      ""
    ],
    "nameDaysShortest": [
      "S",
      "P",
      "A",
      "T",
      "K",
      "P",
      "Š"
    ],
    "nameDaysAbbreviated": [
      "sk",
      "pr",
      "an",
      "tr",
      "kt",
      "pn",
      "št"
    ],
    "nameDays": [
      "sekmadienis",
      "pirmadienis",
      "antradienis",
      "trečiadienis",
      "ketvirtadienis",
      "penktadienis",
      "šeštadienis"
    ],
    "nameCalendarNative": "Grigaliaus kalendorius",
    "nameCalendar": "Gregorian",
    "firstDayOfWeekName": "Monday",
    "firstDayOfWeekIndex": 1,
    "designatorPm": "pop.",
    "designatorAm": "pr.p.",
    "calendarWeekRuleName": "FirstFourDayWeek",
    "calendarWeekRuleIndex": 2
  },
  "code": "lt-LT"
}