{
  "win3": "SWK",
  "separatorList": ",",
  "number": {
    "symbolPositiveInfinity": "Infinity",
    "symbolPerMille": "‰",
    "symbolNegativeInfinity": "-Infinity",
    "symbolNaN": "NaN",
    "symbolCurrency": "Ksh",
    "signPositive": "+",
    "signNegative": "-",
    "separatorGroupPercent": ",",
    "separatorGroupNumber": ",",
    "separatorGroupCurrency": ",",
    "separatorDecimalPercent": ".",
    "separatorDecimalNumber": ".",
    "separatorDecimalCurrency": ".",
    "patternPositivePercent": 0,
    "patternPositiveCurrency": 0,
    "patternNegativePercent": 0,
    "patternNegativeNumber": 1,
    "patternNegativeCurrency": 0,
    "groupSizesPercent": [
      3
    ],
    "groupSizesNumber": [
      3
    ],
    "groupSizesCurrency": [
      3
    ],
    "decimalDigitsPercent": 2,
    "decimalDigitsNumber": 2,
    "decimalDigitsCurrency": 2
  },
  "nameRegionNative": "Kenya",
  "nameRegionEnglish": "Kenya",
  "nameNative": "Kiswahili",
  "nameEnglish": "Swahili",
  "nameDisplay": "Swahili (Kenya)",
  "nameCalendar": "Gregorian",
  "lcid": 1089,
  "isRightToLeft": false,
  "iso3": "swa",
  "iso2": "sw",
  "isNeutral": false,
  "ietf": "sw-KE",
  "dateTime": {
    "separatorTime": ":",
    "separatorDate": "/",
    "patternYearMonth": "MMMM, yyyy",
    "patternUniversalSortable": "yyyy'-'MM'-'dd HH':'mm':'ss'Z'",
    "patternTimeShort": "h:mm tt",
    "patternTimeLong": "h:mm:ss tt",
    "patternRfc1123": "ddd, dd MMM yyyy HH':'mm':'ss 'GMT'",
    "patternMonthDay": "MMMM dd",
    "patternDateTimeSortable": "yyyy'-'MM'-'dd'T'HH':'mm':'ss",
    "patternDateTimeFull": "dddd, MMMM dd, yyyy h:mm:ss tt",
    "patternDateShort": "M/d/yyyy",
    "patternDateLong": "dddd, MMMM dd, yyyy",
    "nameMonthGenitivesAbbreviated": [
      "Jan",
      "Feb",
      "Mac",
      "Apr",
      "Mei",
      "Jun",
      "Jul",
      "Ago",
      "Sep",
      "Okt",
      "Nov",
      "Des",
      ""
    ],
    "nameMonthGenitives": [
      "Januari",
      "Februari",
      "Machi",
      "Aprili",
      "Mei",
      "Juni",
      "Julai",
      "Agosti",
      "Septemba",
      "Oktoba",
      "Novemba",
      "Desemba",
      ""
    ],
    "nameMonthsAbbreviated": [
      "Jan",
      "Feb",
      "Mac",
      "Apr",
      "Mei",
      "Jun",
      "Jul",
      "Ago",
      "Sep",
      "Okt",
      "Nov",
      "Des",
      ""
    ],
    "nameMonths": [
      "Januari",
      "Februari",
      "Machi",
      "Aprili",
      "Mei",
      "Juni",
      "Julai",
      "Agosti",
      "Septemba",
      "Oktoba",
      "Novemba",
      "Desemba",
      ""
    ],
    "nameDaysShortest": [
      "2",
      "3",
      "4",
      "5",
      "A",
      "I",
      "1"
    ],
    "nameDaysAbbreviated": [
      "J2",
      "J3",
      "J4",
      "J5",
      "Alh",
      "Ij",
      "J1"
    ],
    "nameDays": [
      "Jumapili",
      "Jumatatu",
      "Jumanne",
      "Jumatano",
      "Alhamisi",
      "Ijumaa",
      "Jumamosi"
    ],
    "nameCalendarNative": "Kalenda ya Kigregori",
    "nameCalendar": "Gregorian",
    "firstDayOfWeekName": "Sunday",
    "firstDayOfWeekIndex": 0,
    "designatorPm": "PM",
    "designatorAm": "AM",
    "calendarWeekRuleName": "FirstDay",
    "calendarWeekRuleIndex": 0
  },
  "code": "sw-KE"
}