{"signNeg":"-","signPos":"+","symbolPercent":"%","date":{"days":["Якшәмбе","Дүшәмбе","Сишәмбе","Чәршәмбе","Пәнҗешәмбе","Җомга","Шимбә"],"months":["Гыйнварь","Февраль","Март","Апрель","Май","Июнь","Июль","Август","Сентябрь","Октябрь","Ноябрь","Декабрь",""],"patternTime":"%k:%M:%S","firstWeekDay":1,"patternDateShort":"%d.%m.%Y","am":null,"pm":null,"abbrMonths":["Гыйнв","Фев","Мар","Апр","Май","Июн","Июл","Авг","Сен","Окт","Ноя","Дек",""],"patternDateRfc":"%a, %d %b %Y %H:%M:%S GMT","shortDays":["Якш","Дүш","Сиш","Чәрш","Пәнҗ","Җом","Шим"],"abbrDays":["Якш","Дүш","Сиш","Чәрш","Пәнҗ","Җом","Шим"],"patternSortable":"%Y-%m-%dT%H:%M:%S","patternDateTime":"%e %B %Y %k:%M:%S","separatorDate":".","patternUniversal":"%Y-%m-%d %H:%M:%SZ","patternTimeShort":"%k:%M","separatorTime":":","patternYearMonth":"%B %Y","patternMonthDay":"%e %B","patternDate":"%e %B %Y"},"iso2":"RU","iso3":"RUS","name":"tt-RU","currencyIso":"RUR","symbolNaN":"NaN","isMetric":false,"pluralRule":0,"percent":{"decimalsSeparator":",","groupsSeparator":" ","decimals":2,"patternPositive":"n%","groups":[3],"patternNegative":"-n%"},"english":"Tatar (Russia)","language":{"iso2":"tt","iso3":"tat","name":"tt","pluralRule":0,"english":"Tatar","native":"Татар"},"symbolPermille":"‰","symbolNegInf":"-Infinity","nativeCurrency":"рубль","englishRegion":"Russia","currency":{"decimalsSeparator":",","groupsSeparator":" ","decimals":2,"patternPositive":"n $","groups":[3],"patternNegative":"-n $"},"symbolPosInf":"Infinity","englishCurrency":"Russian Ruble","number":{"decimalsSeparator":",","groupsSeparator":" ","decimals":2,"patternPositive":"n","groups":[3],"patternNegative":"-n"},"native":"Татар (Россия)","nativeRegion":"Россия","currencySymbol":"р."}