{
  "nameCalendar": "Gregorian",
  "number": {
    "symbolPositiveInfinity": "Infinity",
    "signPositive": "+",
    "separatorGroupNumber": ",",
    "separatorDecimalPercent": ".",
    "signNegative": "-",
    "symbolCurrency": "R",
    "symbolPerMille": "‰",
    "groupSizesNumber": [
      3
    ],
    "symbolNegativeInfinity": "-Infinity",
    "separatorGroupPercent": ",",
    "symbolNaN": "I-NaN",
    "separatorDecimalNumber": ".",
    "groupSizesCurrency": [
      3
    ],
    "separatorGroupCurrency": ",",
    "separatorDecimalCurrency": ".",
    "groupSizesPercent": [
      3
    ],
    "patternNegativeCurrency": 2,
    "patternNegativePercent": 2,
    "patternPositivePercent": 2,
    "patternPositiveCurrency": 2,
    "decimalDigitsNumber": 2,
    "decimalDigitsCurrency": 2,
    "patternNegativeNumber": 1,
    "decimalDigitsPercent": 2
  },
  "nameNative": "isiZulu",
  "separatorList": ",",
  "nameRegionNative": "i-South Africa",
  "code": "zu-ZA",
  "ietf": "zu-ZA",
  "iso2": "zu",
  "iso3": "zul",
  "nameRegionEnglish": "South Africa",
  "win3": "ZUL",
  "dateTime": {
    "nameCalendar": "Gregorian",
    "patternUniversalSortable": "yyyy'-'MM'-'dd HH':'mm':'ss'Z'",
    "patternDateTimeFull": "dd MMMM yyyy hh:mm:ss tt",
    "nameCalendarNative": "i-Gregorian Calender",
    "calendarWeekRuleName": "FirstDay",
    "patternDateLong": "dd MMMM yyyy",
    "patternDateTimeSortable": "yyyy'-'MM'-'dd'T'HH':'mm':'ss",
    "nameDaysShortest": [
      "S",
      "M",
      "B",
      "T",
      "S",
      "H",
      "M"
    ],
    "firstDayOfWeekName": "Sunday",
    "nameMonthGenitives": [
      "Januwari",
      "Februwari",
      "Mashi",
      "Apreli",
      "Meyi",
      "Juni",
      "Julayi",
      "Agasti",
      "Septhemba",
      "Okthoba",
      "Novemba",
      "Disemba",
      ""
    ],
    "separatorDate": "-",
    "nameMonthGenitivesAbbreviated": [
      "Jan",
      "Feb",
      "Mas",
      "Apr",
      "Mey",
      "Jun",
      "Jul",
      "Aga",
      "Sep",
      "Okt",
      "Nov",
      "Dis",
      ""
    ],
    "designatorAm": "AM",
    "designatorPm": "PM",
    "nameDaysAbbreviated": [
      "Son",
      "Mso",
      "Bil",
      "Tha",
      "Sin",
      "Hla",
      "Mgq"
    ],
    "patternTimeShort": "hh:mm tt",
    "separatorTime": ":",
    "patternTimeLong": "hh:mm:ss tt",
    "patternYearMonth": "MMMM yyyy",
    "patternMonthDay": "d MMMM",
    "nameDays": [
      "Sonto",
      "Msombuluko",
      "Lwesibili",
      "Lwesithathu",
      "Lwesine",
      "Lwesihlanu",
      "Mgqibelo"
    ],
    "nameMonthsAbbreviated": [
      "Jan",
      "Feb",
      "Mas",
      "Apr",
      "Mey",
      "Jun",
      "Jul",
      "Aga",
      "Sep",
      "Okt",
      "Nov",
      "Dis",
      ""
    ],
    "nameMonths": [
      "uJanuwari",
      "uFebruwari",
      "uMashi",
      "u-Apreli",
      "uMeyi",
      "uJuni",
      "uJulayi",
      "uAgasti",
      "uSepthemba",
      "u-Okthoba",
      "uNovemba",
      "uDisemba",
      ""
    ],
    "patternDateShort": "dd-MM-yyyy",
    "patternRfc1123": "ddd, dd MMM yyyy HH':'mm':'ss 'GMT'",
    "firstDayOfWeekIndex": 0,
    "calendarWeekRuleIndex": 0
  },
  "nameEnglish": "Zulu",
  "isNeutral": false,
  "isRightToLeft": false,
  "lcid": 1077
}